MANIFEST.in
README.rst
setup.py
benchmark/benchmark.py
benchmark/markdown-syntax.md
benchmark/requirements.txt
benchmark/test.py
hoedown.egg-info/PKG-INFO
hoedown.egg-info/SOURCES.txt
hoedown.egg-info/dependency_links.txt
hoedown.egg-info/requires.txt
hoedown.egg-info/top_level.txt
hoedownpy/_hoedown.pxd
hoedownpy/_version.py
hoedownpy/hoedown.c
hoedownpy/hoedown.pyx
hoedownpy/wrapper.c
hoedownpy/wrapper.h
hoedownpy/wrapper.pxd
hoedownpy/_hoedown/LICENSE
hoedownpy/_hoedown/Makefile
hoedownpy/_hoedown/Makefile.win
hoedownpy/_hoedown/README.md
hoedownpy/_hoedown/hoedown.def
hoedownpy/_hoedown/html_block_names.gperf
hoedownpy/_hoedown/src/autolink.c
hoedownpy/_hoedown/src/autolink.h
hoedownpy/_hoedown/src/buffer.c
hoedownpy/_hoedown/src/buffer.h
hoedownpy/_hoedown/src/document.c
hoedownpy/_hoedown/src/document.h
hoedownpy/_hoedown/src/escape.c
hoedownpy/_hoedown/src/escape.h
hoedownpy/_hoedown/src/html.c
hoedownpy/_hoedown/src/html.h
hoedownpy/_hoedown/src/html_blocks.c
hoedownpy/_hoedown/src/html_smartypants.c
hoedownpy/_hoedown/src/stack.c
hoedownpy/_hoedown/src/stack.h
hoedownpy/_hoedown/src/version.c
hoedownpy/_hoedown/src/version.h
hoedownpy/_hoedown/test/MarkdownTest_1.0.3/MarkdownTest.pl
hoedownpy/_hoedown/test/MarkdownTest_1.0.3/Tests/Amps and angle encoding.html
hoedownpy/_hoedown/test/MarkdownTest_1.0.3/Tests/Amps and angle encoding.text
hoedownpy/_hoedown/test/MarkdownTest_1.0.3/Tests/Auto links.html
hoedownpy/_hoedown/test/MarkdownTest_1.0.3/Tests/Auto links.text
hoedownpy/_hoedown/test/MarkdownTest_1.0.3/Tests/Backslash escapes.html
hoedownpy/_hoedown/test/MarkdownTest_1.0.3/Tests/Backslash escapes.text
hoedownpy/_hoedown/test/MarkdownTest_1.0.3/Tests/Blockquotes with code blocks.html
hoedownpy/_hoedown/test/MarkdownTest_1.0.3/Tests/Blockquotes with code blocks.text
hoedownpy/_hoedown/test/MarkdownTest_1.0.3/Tests/Code Blocks.html
hoedownpy/_hoedown/test/MarkdownTest_1.0.3/Tests/Code Blocks.text
hoedownpy/_hoedown/test/MarkdownTest_1.0.3/Tests/Code Spans.html
hoedownpy/_hoedown/test/MarkdownTest_1.0.3/Tests/Code Spans.text
