Metadata-Version: 2.1
Name: hoedown
Version: 0.3.0
Summary: The Python binding for Hoedown, a markdown parsing library.
Home-page: https://github.com/hhatto/python-hoedown
Author: Hideo Hattori
Author-email: hhatto.jp@gmail.com
License: MIT
Platform: UNKNOWN
Classifier: Development Status :: 4 - Beta
Classifier: Intended Audience :: Developers
Classifier: License :: OSI Approved :: MIT License
Classifier: Programming Language :: C
Classifier: Programming Language :: Cython
Classifier: Programming Language :: Python :: 2.7
Classifier: Programming Language :: Python :: 3.5
Classifier: Topic :: Text Processing :: Markup
Classifier: Topic :: Text Processing :: Markup :: HTML
Classifier: Topic :: Utilities
Provides-Extra: dev
